pgOperations/__init__.py
pgOperations/pgOperations.py
pgOperations/test.py
pgoperations-0.0.3.dist-info/METADATA
pgoperations-0.0.3.dist-info/WHEEL
pgoperations-0.0.3.dist-info/licenses/LICENSE
pgoperations-0.0.3.dist-info/RECORD
