Metadata-Version: 2.1
Name: pgOperations
Version: 0.0.3
Summary: Simple tool to perform the most common operations in PostgreSQL and PostGIS with Psycopg2. Builds the SQL queries from Pyhton dictionaries.
Project-URL: Repository, https://github.com/joamona/pgOperations
Project-URL: Documentation, https://joamona.github.io/pgOperations/
Author-email: Gaspar Mora-Navarro <joamona@cgf.upv.es>
License-File: LICENSE
Keywords: PostGIS,PostgreSQL,Psycopg2,Utilities
Classifier: License :: OSI Approved :: GNU General Public License (GPL)
Classifier: Operating System :: OS Independent
Classifier: Programming Language :: Python :: 3
Classifier: Topic :: Database
Classifier: Topic :: Software Development :: Libraries :: Python Modules
Requires-Python: >=3
Requires-Dist: psycopg2
